{
  "name": "uploads/howtos/UDaRgClKlDljxxFHyKsX/0-18fb6035d59.jpg",
  "bucket": "default-bucket",
  "metageneration": 1,
  "generation": 1716745625971,
  "contentType": "image/jpeg",
  "storageClass": "STANDARD",
  "contentDisposition": "inline",
  "downloadTokens": ["269b9fea-191d-4df2-be62-05c6293d59e8"],
  "etag": "U/EZ0QlpjgqNMIiGDCRRh4O0M4Q",
  "customMetadata": {},
  "timeCreated": "2024-05-26T17:47:05.971Z",
  "updated": "2024-05-26T17:47:05.971Z",
  "size": 101464,
  "md5Hash": "tlu4Ai3wQVBPI1Bk6NB7eQ==",
  "crc32c": "3209819119"
}
