{
  "name": "uploads/howtos/UDaRgClKlDljxxFHyKsX/4-18fb60328e3.jpg",
  "bucket": "default-bucket",
  "metageneration": 1,
  "generation": 1716745626056,
  "contentType": "image/jpeg",
  "storageClass": "STANDARD",
  "contentDisposition": "inline",
  "downloadTokens": ["62c680ae-6717-485e-8bef-43726d73d00a"],
  "etag": "pRDx9CLvKn62C9kzx4AFwUhivkE",
  "customMetadata": {},
  "timeCreated": "2024-05-26T17:47:06.056Z",
  "updated": "2024-05-26T17:47:06.056Z",
  "size": 60814,
  "md5Hash": "VmzZq8sK2od3snVOMkN8fw==",
  "crc32c": "3186773085"
}
