{
  "kind": "identitytoolkit#DownloadAccountResponse",
  "users": [
    {
      "localId": "2djSop7XvY0NEg7QY5rZrm0Wc2N1",
      "createdAt": "1716744480141",
      "lastLoginAt": "1716746234545",
      "displayName": "admin",
      "passwordHash": "fakeHash:salt=fakeSaltRpTXy52dXY1DgyPT6odF:password=wow_backend_development_is_fun",
      "salt": "fakeSaltRpTXy52dXY1DgyPT6odF",
      "passwordUpdatedAt": 1717874742293,
      "providerUserInfo": [
        {
          "providerId": "password",
          "email": "admin@example.com",
          "federatedId": "admin@example.com",
          "rawId": "admin@example.com",
          "displayName": "admin"
        }
      ],
      "validSince": "1717874742",
      "email": "admin@example.com",
      "emailVerified": false,
      "disabled": false
    },
    {
      "localId": "WrCrfu7FS3vJcFswZr1yufwlPtCl",
      "createdAt": "1716745327556",
      "lastLoginAt": "1716745935132",
      "displayName": "precious-plastic",
      "passwordHash": "fakeHash:salt=fakeSalt5z1E4omMRGeny2KD9xUb:password=precious-plastic",
      "salt": "fakeSalt5z1E4omMRGeny2KD9xUb",
      "passwordUpdatedAt": 1717874742293,
      "providerUserInfo": [
        {
          "providerId": "password",
          "email": "precious-plastic@example.com",
          "federatedId": "precious-plastic@example.com",
          "rawId": "precious-plastic@example.com",
          "displayName": "precious-plastic"
        }
      ],
      "validSince": "1717874742",
      "email": "precious-plastic@example.com",
      "emailVerified": false,
      "disabled": false
    },
    {
      "localId": "nOhRNkqNlKTRdsMsFUjr4Q604ebH",
      "lastLoginAt": "1717875372455",
      "emailVerified": false,
      "email": "mattia@example.com",
      "salt": "fakeSaltZ1DfforKlkMgDcyBR88q",
      "passwordHash": "fakeHash:salt=fakeSaltZ1DfforKlkMgDcyBR88q:password=whoop_whoop_123",
      "passwordUpdatedAt": 1717875372455,
      "validSince": "1717875372",
      "createdAt": "1717875372455",
      "providerUserInfo": [
        {
          "providerId": "password",
          "email": "mattia@example.com",
          "federatedId": "mattia@example.com",
          "rawId": "mattia@example.com",
          "displayName": "mattia"
        }
      ],
      "lastRefreshAt": "2024-06-08T19:36:12.456Z",
      "displayName": "mattia"
    },
    {
      "localId": "uf0mBGfLKGQwoJ1FWiqH0xQSatKM",
      "createdAt": "1716746026812",
      "lastLoginAt": "1716746297841",
      "displayName": "normal_jim",
      "passwordHash": "fakeHash:salt=fakeSalt88tfIY4E8ASJgTGvE3th:password=thanks_emulator_man",
      "salt": "fakeSalt88tfIY4E8ASJgTGvE3th",
      "passwordUpdatedAt": 1717874742293,
      "providerUserInfo": [
        {
          "providerId": "password",
          "email": "normal_jim@example.com",
          "federatedId": "normal_jim@example.com",
          "rawId": "normal_jim@example.com",
          "displayName": "normal_jim"
        }
      ],
      "validSince": "1717874742",
      "email": "normal_jim@example.com",
      "emailVerified": false,
      "disabled": false
    }
  ]
}
